scheduler.sv
module scheduler #(
    parameter MATRIX_SIZE = 2, 
    parameter DATA_SIZE = 32
) (
    input wire clk, reset, general_enable, 
    output wire [MATRIX_SIZE-1:0] load_weight,     // each bit controls one row
    output wire [MATRIX_SIZE-1:0] enable_mult,     // each bit controls one row
    // output wire done_load_wire,
    output wire done
);
    
    // internal signals
    reg[MATRIX_SIZE:0] load_counter;
    reg[MATRIX_SIZE+2 : 0] mult_counter;
    reg done_load;      // internal signal that indicates loading is finished
    reg done_next;
    
    // signals for pipelining
    reg[MATRIX_SIZE-1:0] load_weight_next;
    reg[MATRIX_SIZE-1:0] enable_mult_next;
    reg [MATRIX_SIZE-1:0] load_weight_reg;     // each bit controls one row
    reg [MATRIX_SIZE-1:0] enable_mult_reg;     // each bit controls one row
    reg done_reg;

    // initialize signals
    // initial begin
    //     load_weight_next = {MATRIX_SIZE{1'b0}};
    //     enable_mult_next = {MATRIX_SIZE{1'b0}};
    //     load_counter = 0;
    //     mult_counter = 0;
    //     done_load = 0;
    //     done_next = 0;
    // end

    always @ (posedge clk) begin
        if (load_counter < MATRIX_SIZE)
        begin
            if (load_counter < MATRIX_SIZE-1)
            begin
                load_weight_next = {MATRIX_SIZE{1'b1}};
                load_counter += 1;
            end
            else 
            begin   
                //load_weight_next = {0, (MATRIX_SIZE-1){1'b1}}
                load_weight_next = {MATRIX_SIZE{1'b1}};
                done_load = 1;
                //enable_mult = {1'b1, MATRIX_SIZE{1'b0}};    // once the last row is loaded, start multplying
            end
        end
    end

    always @ (posedge clk) begin
        if (done_next == 0) begin
            if (done_load == 1 && mult_counter[1:0] == 2'b00) begin        // every 4 cycles, enable another row of PE
                enable_mult_next = {1'b1, {MATRIX_SIZE-1{1'b0}}} | (enable_mult>>1);     // adding a 1 to the MSB
                mult_counter += 1;
            end
            else 
            begin
                mult_counter += 1;
            end
            
            if (mult_counter >= ((2*MATRIX_SIZE - 1) * 4)) begin        // need (2n-1)*4 cycles to finish up all the operations 
                done_next = 1;
            end
        end
    end

    always @(posedge clk or posedge reset) begin
        if (reset) begin
            load_weight_next = {MATRIX_SIZE{1'b0}};
            enable_mult_next = {MATRIX_SIZE{1'b0}};
            load_counter = 0;
            mult_counter = 0;
            done_load = 0;
            done_next = 0;
            // done <= 0;
            // enable_mult <= 0;
            // load_weight <= 0;
        end
        else if (general_enable) begin

            done_reg <= done_next;
            enable_mult_reg <= enable_mult_next;
            load_weight_reg <= load_weight_next;
        end
    end

    // assign done_load_wire = done_load;
    assign done = done_reg;
    assign enable_mult = enable_mult_reg;
    assign load_weight = load_weight_reg;
    
endmodule

trace.vcd
$version Generated by VerilatedVcd $end
$date Mon May  2 18:36:05 2022
 $end
$timescale   1ns $end

 $scope module TOP $end
  $var wire  1 k clk $end
  $var wire  1 5! done $end
  $var wire  2 -! enable_mult [1:0] $end
  $var wire  1 { general_enable $end
  $var wire  2 %! load_weight [1:0] $end
  $var wire  1 s reset $end
  $scope module scheduler $end
   $var wire 32 E! DATA_SIZE [31:0] $end
   $var wire 32 =! MATRIX_SIZE [31:0] $end
   $var wire  1 k clk $end
   $var wire  1 5! done $end
   $var wire  1 3 done_load $end
   $var wire  1 ; done_next $end
   $var wire  1 c done_reg $end
   $var wire  2 -! enable_mult [1:0] $end
   $var wire  2 K enable_mult_next [1:0] $end
   $var wire  2 [ enable_mult_reg [1:0] $end
   $var wire  1 { general_enable $end
   $var wire  3 # load_counter [2:0] $end
   $var wire  2 %! load_weight [1:0] $end
   $var wire  2 C load_weight_next [1:0] $end
   $var wire  2 S load_weight_reg [1:0] $end
   $var wire  5 + mult_counter [4:0] $end
   $var wire  1 s reset $end
  $upscope $end
 $upscope $end
$enddefinitions $end


#0
b000 #
b00000 +
03
0;
b00 C
b00 K
b00 S
b00 [
0c
1k
1s
0{
b00 %!
b00 -!
05!
b00000000000000000000000000000010 =!
b00000000000000000000000000100000 E!
#1
#2
#3
#4
#5
0k
#6
#7
#8
#9
#10
b001 #
b00001 +
b11 C
b11 S
1k
0s
1{
b11 %!
#11
#12
#13
#14
#15
0k
#16
#17
#18
#19
#20
b00010 +
13
1k
#21
#22
#23
#24
#25
0k
#26
#27
#28
#29
#30
b00011 +
1k
#31
#32
#33
#34
#35
0k
#36
#37
#38
#39
#40
b00100 +
1k
#41
#42
#43
#44
#45
0k
#46
#47
#48
#49
#50
b00101 +
b10 K
b10 [
1k
b10 -!
#51
#52
#53
#54
#55
0k
#56
#57
#58
#59
#60
b00110 +
1k
#61
#62
#63
#64
#65
0k
#66
#67
#68
#69
#70
b00111 +
1k
#71
#72
#73
#74
#75
0k
#76
#77
#78
#79
#80
b01000 +
1k
#81
#82
#83
#84
#85
0k
#86
#87
#88
#89
#90
b01001 +
b11 K
b11 [
1k
b11 -!
#91
#92
#93
#94
#95
0k
#96
#97
#98
#99
#100
b01010 +
1k
#101
#102
#103
#104
#105
0k
#106
#107
#108
#109
#110
b01011 +
1k
#111
#112
#113
#114
#115
0k
#116
#117
#118
#119
#120
b01100 +
1;
1c
1k
15!
